qtoggleserver/cmdline/__init__.py
qtoggleserver/cmdline/exceptions.py
qtoggleserver/cmdline/peripheral.py
qtoggleserver/cmdline/ports.py
qtoggleserver_cmdline-1.3.1.dist-info/licenses/LICENSE.txt
qtoggleserver_cmdline-1.3.1.dist-info/METADATA
qtoggleserver_cmdline-1.3.1.dist-info/WHEEL
qtoggleserver_cmdline-1.3.1.dist-info/top_level.txt
qtoggleserver_cmdline-1.3.1.dist-info/RECORD
