Metadata-Version: 2.4
Name: qtoggleserver-cmdline
Version: 1.3.1
Summary: qToggleServer ports backed by system commands
Author-email: Calin Crisan <ccrisan@gmail.com>
License: Apache 2.0
Requires-Python: >=3.11
License-File: LICENSE.txt
Dynamic: license-file
